pyaescbc/__init__.py
pyaescbc/__main__.py
pyaescbc/__version__.py
pyaescbc/auth_error.py
pyaescbc/check_hmac.py
pyaescbc/cleardata_to_encrypted_bundle.py
pyaescbc/create_encrypted_bundle.py
pyaescbc/create_hmac.py
pyaescbc/decrypt_AES_CBC.py
pyaescbc/delete_bytearray.py
pyaescbc/derive_key.py
pyaescbc/encrypt_AES_CBC.py
pyaescbc/encrypted_bundle_to_cleardata.py
pyaescbc/extract_cryptography_components.py
pyaescbc/generate_pin_iterations.py
pyaescbc/generate_random_iterations.py
pyaescbc/random_bytearray.py
pyaescbc/random_iv.py
pyaescbc/random_salt.py
pyaescbc/resources/__init__.py
pyaescbc/resources/decrypt.png
pyaescbc/resources/encrypt.png
pyaescbc-0.1.5.dist-info/licenses/LICENSE
pyaescbc-0.1.5.dist-info/METADATA
pyaescbc-0.1.5.dist-info/WHEEL
pyaescbc-0.1.5.dist-info/top_level.txt
pyaescbc-0.1.5.dist-info/RECORD
