Metadata-Version: 2.4
Name: pyaescbc
Version: 0.1.5
Summary: AES-CBC encryption tools based on crytography package.
Author-email: Artezaru <artezaru.github@proton.me>
License: Copyright 2025 Artezaru
Project-URL: Homepage, https://github.com/Artezaru/pyaescbc
Project-URL: Documentation, https://Artezaru.github.io/pyaescbc
Project-URL: Source, https://github.com/Artezaru/pyaescbc
Project-URL: Tracker, https://github.com/Artezaru/pyaescbc/issues
Classifier: Programming Language :: Python :: 3
Classifier: License :: OSI Approved :: Apache Software License
Classifier: Operating System :: OS Independent
Requires-Python: >=3.10
License-File: LICENSE
Requires-Dist: cryptography>=39.0.1
Provides-Extra: dev
Requires-Dist: sphinx; extra == "dev"
Requires-Dist: pydata-sphinx-theme; extra == "dev"
Requires-Dist: numpydoc; extra == "dev"
Requires-Dist: pytest; extra == "dev"
Requires-Dist: pytest-cov; extra == "dev"
Requires-Dist: bumpver; extra == "dev"
Requires-Dist: twine; extra == "dev"
Requires-Dist: wheel; extra == "dev"
Requires-Dist: build; extra == "dev"
Requires-Dist: setuptools; extra == "dev"
Requires-Dist: setuptools-scm; extra == "dev"
Dynamic: license-file
